examples/Wv2BinStream.py
examples/fileopening.py
examples/instrumentexamples.py
rskfd/__init__.py
rskfd/logger.py
rskfd/helper/helper.py
rskfd/iq_data_handling/iqdata.py
rskfd/remote_control/instrument.py
rskfd/remote_control/instrumentRS.py
rskfd/remote_control/instrumentRSExceptions.py
rskfd/remote_control/instrumentRS_FSW.py
rskfd/remote_control/instrumentRS_VSE.py
rskfd/signal_generation/signal_generation.py
rskfd/snp_handling/snpfiles.py
rskfd-0.5.6.dist-info/METADATA
rskfd-0.5.6.dist-info/WHEEL
rskfd-0.5.6.dist-info/license.txt
rskfd-0.5.6.dist-info/top_level.txt
rskfd-0.5.6.dist-info/RECORD
