Metadata-Version: 2.1
Name: rskfd
Version: 0.5.6
Summary: Python Package for Instrument Control and Data Handling
Home-page: https://gitlab.com/ramian/rskfd
Download-URL: https://gitlab.com/ramian/rskfd/
Author: Florian Ramian
Author-email: gitlab@ramian.eu
License: MIT
Keywords: INSTRUMENT CONTROL,I/Q DATA,WV,IQ.TAR
Classifier: Development Status :: 4 - Beta
Classifier: Intended Audience :: Developers
Classifier: Topic :: Scientific/Engineering
Classifier: Topic :: Scientific/Engineering :: Electronic Design Automation (EDA)
Classifier: Topic :: Software Development :: Libraries :: Python Modules
Classifier: License :: OSI Approved :: MIT License
Classifier: Programming Language :: Python :: 3
Requires-Python: >=3.0
License-File: license.txt
Requires-Dist: numpy
Requires-Dist: scipy
